monocle_apptrace/README.md
monocle_apptrace/__init__.py
monocle_apptrace/__main__.py
monocle_apptrace/mcp_server.py
monocle_apptrace/exporters/base_exporter.py
monocle_apptrace/exporters/exporter_processor.py
monocle_apptrace/exporters/file_exporter.py
monocle_apptrace/exporters/monocle_exporters.py
monocle_apptrace/exporters/aws/s3_exporter.py
monocle_apptrace/exporters/aws/s3_exporter_opendal.py
monocle_apptrace/exporters/azure/blob_exporter.py
monocle_apptrace/exporters/azure/blob_exporter_opendal.py
monocle_apptrace/exporters/okahu/okahu_exporter.py
monocle_apptrace/instrumentation/__init__.py
monocle_apptrace/instrumentation/common/__init__.py
monocle_apptrace/instrumentation/common/constants.py
monocle_apptrace/instrumentation/common/instrumentor.py
monocle_apptrace/instrumentation/common/method_wrappers.py
monocle_apptrace/instrumentation/common/scope_wrapper.py
monocle_apptrace/instrumentation/common/span_handler.py
monocle_apptrace/instrumentation/common/tracing.md
monocle_apptrace/instrumentation/common/utils.py
monocle_apptrace/instrumentation/common/wrapper.py
monocle_apptrace/instrumentation/common/wrapper_method.py
monocle_apptrace/instrumentation/metamodel/__init__.py
monocle_apptrace/instrumentation/metamodel/finish_types.py
monocle_apptrace/instrumentation/metamodel/a2a/__init__.py
monocle_apptrace/instrumentation/metamodel/a2a/_helper.py
monocle_apptrace/instrumentation/metamodel/a2a/methods.py
monocle_apptrace/instrumentation/metamodel/a2a/entities/__init__.py
monocle_apptrace/instrumentation/metamodel/a2a/entities/inference.py
monocle_apptrace/instrumentation/metamodel/adk/__init__.py
monocle_apptrace/instrumentation/metamodel/adk/_helper.py
monocle_apptrace/instrumentation/metamodel/adk/methods.py
monocle_apptrace/instrumentation/metamodel/adk/entities/agent.py
monocle_apptrace/instrumentation/metamodel/adk/entities/tool.py
monocle_apptrace/instrumentation/metamodel/agents/__init__.py
monocle_apptrace/instrumentation/metamodel/agents/_helper.py
test_apptrace-0.5.7.dist-info/METADATA
test_apptrace-0.5.7.dist-info/WHEEL
test_apptrace-0.5.7.dist-info/entry_points.txt
test_apptrace-0.5.7.dist-info/licenses/LICENSE
test_apptrace-0.5.7.dist-info/licenses/NOTICE
test_apptrace-0.5.7.dist-info/RECORD
